{
  "meta": {
    "generated_at": "2026-04-22T19:24:26.305383+00:00",
    "status": "fresh",
    "source": "oilpriceapi",
    "endpoint": "https://api.oilpriceapi.com/v1/prices/all",
    "last_success": "2026-04-22T19:24:26.305383+00:00"
  },
  "prices": {
    "Brent Crude": {
      "price": 101.92,
      "change": 4.71,
      "pct": 4.84,
      "unit": "$/bbl",
      "source_code": "BRENT_CRUDE_USD",
      "updated_at": "2026-04-22T19:19:53Z"
    },
    "Diesel ULSD": {
      "price": 3.93,
      "change": 0.23,
      "pct": 6.22,
      "unit": "$/gal",
      "source_code": "DIESEL_USD",
      "updated_at": "2026-04-22T19:10:14Z"
    },
    "Dutch TTF Natural Gas": {
      "price": 43.93,
      "change": 1.48,
      "pct": 3.49,
      "unit": "EUR/MWh",
      "source_code": "DUTCH_TTF_EUR",
      "updated_at": "2026-04-22T15:56:16Z"
    },
    "Gasoline RBOB": {
      "price": 3.35,
      "change": 0.16,
      "pct": 5.02,
      "unit": "$/gal",
      "source_code": "GASOLINE_USD",
      "updated_at": "2026-04-22T18:25:15Z"
    },
    "Heating Oil": {
      "price": 3.93,
      "change": 0.24,
      "pct": 6.49,
      "unit": "$/gal",
      "source_code": "HEATING_OIL_USD",
      "updated_at": "2026-04-22T19:19:58Z"
    },
    "Jet Fuel": {
      "price": 3.74,
      "change": 0.0,
      "pct": 0.0,
      "unit": "$/gal",
      "source_code": "JET_FUEL_USD",
      "updated_at": "2026-04-15T21:00:44Z"
    },
    "JKM LNG (Japan/Korea)": {
      "price": 16.12,
      "change": 0.31,
      "pct": 1.96,
      "unit": "$/MMBtu",
      "source_code": "JKM_LNG_USD",
      "updated_at": "2026-04-22T17:10:55Z"
    },
    "Natural Gas": {
      "price": 2.71,
      "change": 0.01,
      "pct": 0.37,
      "unit": "$/MMBtu",
      "source_code": "NATURAL_GAS_USD",
      "updated_at": "2026-04-22T19:16:39Z"
    },
    "Coal": {
      "price": 133.75,
      "change": 0.0,
      "pct": 0.0,
      "unit": "$/ton",
      "source_code": "NEWCASTLE_COAL_USD",
      "updated_at": "2026-04-22T00:00:34Z"
    },
    "WTI Crude": {
      "price": 92.95,
      "change": 4.23,
      "pct": 4.76,
      "unit": "$/bbl",
      "source_code": "WTI_USD",
      "updated_at": "2026-04-22T19:19:54Z"
    }
  }
}